finding/__init__.py
finding-0.0.1.dist-info/LICENSE
finding-0.0.1.dist-info/METADATA
finding-0.0.1.dist-info/WHEEL
finding-0.0.1.dist-info/RECORD
