Metadata-Version: 2.1
Name: finding
Version: 0.0.1
Summary: 
License: MIT
Author: CHUA-X
Author-email: chua-x@outlook.com
Requires-Python: >=3.6,<3.7
Classifier: License :: OSI Approved :: MIT License
Classifier: Programming Language :: Python :: 3
Classifier: Programming Language :: Python :: 3.6
